plotoptix-0.18.4.data/purelib/plotoptix/__init__.py
plotoptix-0.18.4.data/purelib/plotoptix/_load_lib.py
plotoptix-0.18.4.data/purelib/plotoptix/enums.py
plotoptix-0.18.4.data/purelib/plotoptix/geometry.py
plotoptix-0.18.4.data/purelib/plotoptix/materials.py
plotoptix-0.18.4.data/purelib/plotoptix/npoptix.py
plotoptix-0.18.4.data/purelib/plotoptix/singleton.py
plotoptix-0.18.4.data/purelib/plotoptix/tkoptix.py
plotoptix-0.18.4.data/purelib/plotoptix/utils.py
plotoptix-0.18.4.data/purelib/plotoptix/bin/BitMiracle.LibTiff.NET.dll
plotoptix-0.18.4.data/purelib/plotoptix/bin/BitMiracle.LibTiff.NET.xml
plotoptix-0.18.4.data/purelib/plotoptix/bin/Newtonsoft.Json.dll
plotoptix-0.18.4.data/purelib/plotoptix/bin/Newtonsoft.Json.xml
plotoptix-0.18.4.data/purelib/plotoptix/bin/RnD.SharpEncoder.dll
plotoptix-0.18.4.data/purelib/plotoptix/bin/RnD.SharpOptiX.dll
plotoptix-0.18.4.data/purelib/plotoptix/bin/RnD.SharpOptiX.dll.config
plotoptix-0.18.4.data/purelib/plotoptix/bin/libOpenImageDenoise.so
plotoptix-0.18.4.data/purelib/plotoptix/bin/libOpenImageDenoise_core.so.2.3.1
plotoptix-0.18.4.data/purelib/plotoptix/bin/libOpenImageDenoise_device_cuda.so.2.3.1
plotoptix-0.18.4.data/purelib/plotoptix/bin/librndSharpEncoder.so
plotoptix-0.18.4.data/purelib/plotoptix/bin/librndSharpOptiX7.so
plotoptix-0.18.4.data/purelib/plotoptix/bin/cuda/ahit7_occlusion.ir
plotoptix-0.18.4.data/purelib/plotoptix/bin/cuda/camera7_custom_proj.ir
plotoptix-0.18.4.data/purelib/plotoptix/bin/cuda/camera7_custom_proj_xyz.ir
plotoptix-0.18.4.data/purelib/plotoptix/bin/cuda/camera7_custom_proj_xyz2dir.ir
plotoptix-0.18.4.data/purelib/plotoptix/bin/cuda/camera7_custom_proj_xyz2xyz.ir
plotoptix-0.18.4.data/purelib/plotoptix/bin/cuda/camera7_fisheye.ir
plotoptix-0.18.4.data/purelib/plotoptix/bin/cuda/camera7_fisheye_chroma.ir
plotoptix-0.18.4.data/purelib/plotoptix/bin/cuda/camera7_fisheye_chroma_noise_lim.ir
plotoptix-0.18.4.data/purelib/plotoptix/bin/cuda/camera7_fisheye_noise_lim.ir
plotoptix-0.18.4.dist-info/LICENSE.txt
plotoptix-0.18.4.dist-info/METADATA
plotoptix-0.18.4.dist-info/WHEEL
plotoptix-0.18.4.dist-info/top_level.txt
plotoptix-0.18.4.dist-info/RECORD
