Metadata-Version: 2.1
Name: plotoptix
Version: 0.18.4
Summary: Data visualisation in Python based on NVIDIA OptiX ray tracing framework.
Home-page: https://rnd.team/plotoptix
Author: Robert Sulej, R&D Team
Author-email: dev@rnd.team
License: UNKNOWN
Project-URL: Documentation, https://plotoptix.rnd.team
Project-URL: Examples, https://github.com/rnd-team-dev/plotoptix/tree/master/examples
Project-URL: Source, https://github.com/rnd-team-dev/plotoptix
Keywords: gpu nvidia optix ray-tracing path-tracing visualisation generative plot animation real-time
Platform: UNKNOWN
Classifier: Development Status :: 4 - Beta
Classifier: Environment :: Win32 (MS Windows)
Classifier: Environment :: X11 Applications
Classifier: Operating System :: Microsoft :: Windows
Classifier: Operating System :: POSIX :: Linux
Classifier: Programming Language :: Python :: 3 :: Only
Classifier: Intended Audience :: Education
Classifier: Intended Audience :: End Users/Desktop
Classifier: Intended Audience :: Science/Research
Classifier: License :: Free for non-commercial use
Classifier: Natural Language :: English
Classifier: Topic :: Multimedia :: Graphics :: 3D Rendering
Classifier: Topic :: Scientific/Engineering :: Visualization
Classifier: Topic :: Artistic Software
License-File: LICENSE.txt
Requires-Dist: packaging (>=18.0)
Requires-Dist: numpy (>=1.0)
Requires-Dist: Pillow (>=5.3)
Requires-Dist: python-dateutil (>=2.7)
Requires-Dist: matplotlib (>=2.0)
Requires-Dist: requests (>=2.25)
Requires-Dist: enum34 ; python_version <= "3.4"
